bintrees/__init__.py
bintrees/abctree.py
bintrees/avltree.py
bintrees/bintree.py
bintrees/cython_trees.cp37-win_amd64.pyd
bintrees/rbtree.py
bintrees/treeslice.py
bintrees-2.1.0.dist-info/LICENSE.txt
bintrees-2.1.0.dist-info/METADATA
bintrees-2.1.0.dist-info/WHEEL
bintrees-2.1.0.dist-info/top_level.txt
bintrees-2.1.0.dist-info/RECORD
