Metadata-Version: 2.1
Name: bintrees
Version: 2.1.0
Summary: Package provides Binary-, RedBlack- and AVL-Trees in Python and Cython.
Home-page: https://github.com/mozman/bintrees.git
Author: mozman
Author-email: me@mozman.at
License: MIT License
Download-URL: https://github.com/mozman/bintrees/releases
Platform: OS Independent
Classifier: Development Status :: 7 - Inactive
Classifier: License :: OSI Approved :: MIT License
Classifier: Operating System :: OS Independent
Classifier: Programming Language :: Python :: 3
Classifier: Programming Language :: Python :: 3.7
Classifier: Programming Language :: Python :: 3.8
Classifier: Programming Language :: Cython
Classifier: Programming Language :: Python :: Implementation :: CPython
Classifier: Programming Language :: Python :: Implementation :: PyPy
Classifier: Intended Audience :: Developers
Classifier: Topic :: Software Development :: Libraries :: Python Modules
Requires-Python: >=3.5
